Workbook

Sheet Dashboard
A1: PageCast Launch Budget Dashboard | B1: PageCast Launch Budget Dashboard | C1: PageCast Launch Budget Dashboard | D1: PageCast Launch Budget Dashboard | E1: PageCast Launch Budget Dashboard | F1: PageCast Launch Budget Dashboard | G1: PageCast Launch Budget Dashboard
A2: Solopreneur launch budget for domain, database, email, infrastructure, content, legal, and operations. | B2: Solopreneur launch budget for domain, database, email, infrastructure, content, legal, and operations. | C2: Solopreneur launch budget for domain, database, email, infrastructure, content, legal, and operations. | D2: Solopreneur launch budget for domain, database, email, infrastructure, content, legal, and operations. | E2: Solopreneur launch budget for domain, database, email, infrastructure, content, legal, and operations. | F2: Solopreneur launch budget for domain, database, email, infrastructure, content, legal, and operations. | G2: Solopreneur launch budget for domain, database, email, infrastructure, content, legal, and operations. | H2: Solopreneur launch budget for domain, database, email, infrastructure, content, legal, and operations.
A4: Budget Summary | B4: Lean | C4: Recommended | D4: Safer Launch
A5: One-time setup total | B5: ='Setup Budget'!B16 -> 1461.9 | C5: ='Setup Budget'!C16 -> 4685.1 | D5: ='Setup Budget'!D16 -> 11770.8
A6: Monthly operating cost | B6: ='Monthly Opex'!B20 -> 305 | C6: ='Monthly Opex'!C20 -> 1097 | D6: ='Monthly Opex'!D20 -> 2841
A7: First 3 months cash needed | B7: =B5+B6*3 -> 2376.9 | C7: =C5+C6*3 -> 7976.1 | D7: =D5+D6*3 -> 20293.8
A8: First 6 months cash needed | B8: =B5+B6*6 -> 3291.9 | C8: =C5+C6*6 -> 11267.1 | D8: =D5+D6*6 -> 28816.8
A9: First 12 months cash needed | B9: =B5+B6*12 -> 5121.9 | C9: =C5+C6*12 -> 17849.1 | D9: =D5+D6*12 -> 45862.8
A10: Selected scenario | B10: =Assumptions!B5 -> Recommended
A11: Model status | B11: =Checks!E9 -> OK
A14: Recommended Launch Budget | B14: What It Means
A15: Minimum viable cash target | B15: Use 3 months of selected scenario budget as the absolute floor.
A16: Practical launch cash target | B16: Use 6 months of selected scenario budget so you can survive slow validation.
A17: Recommended scenario | B17: Recommended: professional enough for public launch without pretending you have a team.
A18: Domain | B18: Budget about $15/year for .com-style domain; confirm checkout price.
A19: Database/Auth | B19: Supabase Pro at launch is safer than free tier once real users and payments arrive.
A20: Email | B20: Use one business inbox plus transactional email for auth, receipts, and creator workflows.
A21: Biggest optional spend | B21: Marketing and launch catalog quality. These can be throttled without breaking the platform.
A22: Biggest risk | B22: Under-budgeting legal/compliance and content quality for a family/children product.

Sheet Assumptions
A1: PageCast Launch Budget Assumptions | B1: PageCast Launch Budget Assumptions | C1: PageCast Launch Budget Assumptions | D1: PageCast Launch Budget Assumptions | E1: PageCast Launch Budget Assumptions | F1: PageCast Launch Budget Assumptions
A2: Solopreneur launch budget. Blue/yellow cells are editable; model outputs update from this tab. | B2: Solopreneur launch budget. Blue/yellow cells are editable; model outputs update from this tab. | C2: Solopreneur launch budget. Blue/yellow cells are editable; model outputs update from this tab. | D2: Solopreneur launch budget. Blue/yellow cells are editable; model outputs update from this tab. | E2: Solopreneur launch budget. Blue/yellow cells are editable; model outputs update from this tab. | F2: Solopreneur launch budget. Blue/yellow cells are editable; model outputs update from this tab. | G2: Solopreneur launch budget. Blue/yellow cells are editable; model outputs update from this tab. | H2: Solopreneur launch budget. Blue/yellow cells are editable; model outputs update from this tab.
A4: Scenario Selector | B4: Scenario Selector | C4: Scenario Selector | D4: Scenario Selector | E4: Scenario Selector | F4: Scenario Selector
A5: Selected Scenario | B5: Recommended | D5: Currency | E5: USD
A8: Setup and Pre-Launch Budget Inputs | B8: Setup and Pre-Launch Budget Inputs | C8: Setup and Pre-Launch Budget Inputs | D8: Setup and Pre-Launch Budget Inputs | E8: Setup and Pre-Launch Budget Inputs | F8: Setup and Pre-Launch Budget Inputs
A9: Cost Item | B9: Lean | C9: Recommended | D9: Safer Launch | E9: Type | F9: Notes
A10: Domain registration / transfer | B10: 12 | C10: 15 | D10: 25 | E10: One-time | F10: .com or similar; renewal may vary
A11: Business email setup | B11: 12 | C11: 84 | D11: 84 | E11: One-time/annual | F11: Zoho low-cost or Google Workspace first year
A12: Legal policy review / templates | B12: 300 | C12: 1000 | D12: 2500 | E12: One-time | F12: Privacy, terms, creator terms, copyright/takedown
A13: Business registration / accounting setup | B13: 150 | C13: 300 | D13: 700 | E13: One-time | F13: Entity, bookkeeping, tax setup
A14: Branding / landing assets | B14: 50 | C14: 250 | D14: 750 | E14: One-time | F14: Logo polish, screenshots, social graphics
A15: Launch catalog production | B15: 500 | C15: 1500 | D15: 3500 | E15: One-time | F15: 10 flagship stories, covers, audio passes, QA
A16: Initial audio/music/SFX library | B16: 75 | C16: 250 | D16: 600 | E16: One-time | F16: Licensed music, SFX, premium voice credits
A17: Compliance / child-safety review buffer | B17: 200 | C17: 600 | D17: 1500 | E17: One-time | F17: Extra review before family/children marketing
A18: Payment test budget | B18: 30 | C18: 75 | D18: 150 | E18: One-time | F18: Test transactions, refunds, payment edge cases
A19: Launch contingency | B19: 0.1 | C19: 0.15 | D19: 0.2 | E19: % | F19: Contingency applied to one-time setup subtotal
A22: Monthly Operating Budget Inputs | B22: Monthly Operating Budget Inputs | C22: Monthly Operating Budget Inputs | D22: Monthly Operating Budget Inputs | E22: Monthly Operating Budget Inputs | F22: Monthly Operating Budget Inputs
A23: Cost Item | B23: Lean | C23: Recommended | D23: Safer Launch | E23: Category | F23: Notes
A24: Hosting - Vercel | B24: 0 | C24: 20 | D24: 20 | E24: Infrastructure | F24: Hobby for early tests; Pro for production/commercial use
A25: Database/Auth - Supabase | B25: 0 | C25: 25 | D25: 25 | E25: Infrastructure | F25: Free for early tests; Pro recommended before launch
A26: Object storage - Cloudflare R2 | B26: 3 | C26: 8 | D26: 20 | E26: Infrastructure | F26: Audio/covers storage buffer; usage based
A27: Transactional email - Resend | B27: 0 | C27: 20 | D27: 20 | E27: Email | F27: Free tier initially; Pro if volume/branding requires
A28: Business email - Google/Zoho | B28: 1 | C28: 7 | D28: 7 | E28: Email | F28: One solopreneur inbox
A29: AI text / assistant tools | B29: 20 | C29: 40 | D29: 80 | E29: AI tools | F29: Writing, support, content ops
A30: AI voice / TTS credits | B30: 6 | C30: 22 | D30: 99 | E30: Audio | F30: Starter/creator/pro depending on production needs
A31: Design tools | B31: 0 | C31: 15 | D31: 20 | E31: Creative | F31: Canva or equivalent
A32: Analytics / monitoring | B32: 0 | C32: 0 | D32: 20 | E32: Infrastructure | F32: Free tier first; paid monitoring buffer
A33: Accounting / invoicing tools | B33: 0 | C33: 15 | D33: 30 | E33: Operations | F33: May start with spreadsheets
A34: Legal/compliance reserve | B34: 50 | C34: 150 | D34: 300 | E34: Operations | F34: Monthly reserve for reviews, notices, admin
A35: Customer support / moderation reserve | B35: 0 | C35: 50 | D35: 150 | E35: Operations | F35: Solo time plus occasional help
... A38: Misc SaaS buffer | B38: 25 | C38: 75 | D38: 150 | E38: Operations | F38: Unexpected tools, plugins, templates
A41: Cash Plan Inputs | B41: Cash Plan Inputs | C41: Cash Plan Inputs | D41: Cash Plan Inputs | E41: Cash Plan Inputs | F41: Cash Plan Inputs
A42: Input | B42: Lean | C42: Recommended | D42: Safer Launch | E42: Unit | F42: Notes
A43: Starting cash available | B43: 3000 | C43: 8000 | D43: 20000 | E43: $ | F43: Cash reserved specifically for PageCast launch
A44: Months before paid launch | B44: 2 | C44: 3 | D44: 4 | E44: months | F44: Pre-launch runway before first revenue
A45: Average paid unlock price | B45: 2.99 | C45: 3.99 | D45: 4.99 | E45: $ | F45: Story unlock price
A46: Creator payout share | B46: 0.65 | C46: 0.6 | D46: 0.55 | E46: % | F46: Share of story unlock GMV paid to creators
A47: Payment processing variable fee | B47: 0.035 | C47: 0.035 | D47: 0.032 | E47: % | F47: Stripe/payment processing assumption

Sheet Setup Budget
A1: One-Time Setup Budget | B1: One-Time Setup Budget | C1: One-Time Setup Budget | D1: One-Time Setup Budget | E1: One-Time Setup Budget | F1: One-Time Setup Budget
A2: Pre-launch cash needed before public launch. | B2: Pre-launch cash needed before public launch. | C2: Pre-launch cash needed before public launch. | D2: Pre-launch cash needed before public launch. | E2: Pre-launch cash needed before public launch. | F2: Pre-launch cash needed before public launch. | G2: Pre-launch cash needed before public launch. | H2: Pre-launch cash needed before public launch.
A4: Item | B4: Lean | C4: Recommended | D4: Safer Launch | E4: Selected | F4: Notes
A5: =Assumptions!A10 -> Domain registration / transfer | B5: =Assumptions!B10 -> 12 | C5: =Assumptions!C10 -> 15 | D5: =Assumptions!D10 -> 25 | E5: =INDEX(B5:D5,1,MATCH(Assumptions!$B$5,$B$4:$D$4,0)) -> 15 | F5: =Assumptions!F10 -> .com or similar; renewal may vary
A6: =Assumptions!A11 -> Business email setup | B6: =Assumptions!B11 -> 12 | C6: =Assumptions!C11 -> 84 | D6: =Assumptions!D11 -> 84 | E6: =INDEX(B6:D6,1,MATCH(Assumptions!$B$5,$B$4:$D$4,0)) -> 84 | F6: =Assumptions!F11 -> Zoho low-cost or Google Workspace first year
A7: =Assumptions!A12 -> Legal policy review / templates | B7: =Assumptions!B12 -> 300 | C7: =Assumptions!C12 -> 1000 | D7: =Assumptions!D12 -> 2500 | E7: =INDEX(B7:D7,1,MATCH(Assumptions!$B$5,$B$4:$D$4,0)) -> 1000 | F7: =Assumptions!F12 -> Privacy, terms, creator terms, copyright/takedown
A8: =Assumptions!A13 -> Business registration / accounting setup | B8: =Assumptions!B13 -> 150 | C8: =Assumptions!C13 -> 300 | D8: =Assumptions!D13 -> 700 | E8: =INDEX(B8:D8,1,MATCH(Assumptions!$B$5,$B$4:$D$4,0)) -> 300 | F8: =Assumptions!F13 -> Entity, bookkeeping, tax setup
A9: =Assumptions!A14 -> Branding / landing assets | B9: =Assumptions!B14 -> 50 | C9: =Assumptions!C14 -> 250 | D9: =Assumptions!D14 -> 750 | E9: =INDEX(B9:D9,1,MATCH(Assumptions!$B$5,$B$4:$D$4,0)) -> 250 | F9: =Assumptions!F14 -> Logo polish, screenshots, social graphics
A10: =Assumptions!A15 -> Launch catalog production | B10: =Assumptions!B15 -> 500 | C10: =Assumptions!C15 -> 1500 | D10: =Assumptions!D15 -> 3500 | E10: =INDEX(B10:D10,1,MATCH(Assumptions!$B$5,$B$4:$D$4,0)) -> 1500 | F10: =Assumptions!F15 -> 10 flagship stories, covers, audio passes, QA
A11: =Assumptions!A16 -> Initial audio/music/SFX library | B11: =Assumptions!B16 -> 75 | C11: =Assumptions!C16 -> 250 | D11: =Assumptions!D16 -> 600 | E11: =INDEX(B11:D11,1,MATCH(Assumptions!$B$5,$B$4:$D$4,0)) -> 250 | F11: =Assumptions!F16 -> Licensed music, SFX, premium voice credits
A12: =Assumptions!A17 -> Compliance / child-safety review buffer | B12: =Assumptions!B17 -> 200 | C12: =Assumptions!C17 -> 600 | D12: =Assumptions!D17 -> 1500 | E12: =INDEX(B12:D12,1,MATCH(Assumptions!$B$5,$B$4:$D$4,0)) -> 600 | F12: =Assumptions!F17 -> Extra review before family/children marketing
A13: =Assumptions!A18 -> Payment test budget | B13: =Assumptions!B18 -> 30 | C13: =Assumptions!C18 -> 75 | D13: =Assumptions!D18 -> 150 | E13: =INDEX(B13:D13,1,MATCH(Assumptions!$B$5,$B$4:$D$4,0)) -> 75 | F13: =Assumptions!F18 -> Test transactions, refunds, payment edge cases
A14: Subtotal before contingency | B14: =SUM(B5:B13) -> 1329 | C14: =SUM(C5:C13) -> 4074 | D14: =SUM(D5:D13) -> 9809 | E14: =SUM(E5:E13) -> 4074
A15: Contingency | B15: =B14*Assumptions!B19 -> 132.9 | C15: =C14*Assumptions!C19 -> 611.1 | D15: =D14*Assumptions!D19 -> 1961.8 | E15: =E14*INDEX(Assumptions!$B$19:$D$19,1,MATCH(Assumptions!$B$5,Assumptions!$B$9:$D$9,0)) -> 611.1
A16: Total setup budget | B16: =B14+B15 -> 1461.9 | C16: =C14+C15 -> 4685.1 | D16: =D14+D15 -> 11770.8 | E16: =E14+E15 -> 4685.1

Sheet Monthly Opex
A1: Monthly Operating Budget | B1: Monthly Operating Budget | C1: Monthly Operating Budget | D1: Monthly Operating Budget | E1: Monthly Operating Budget | F1: Monthly Operating Budget | G1: Monthly Operating Budget
A2: Recurring monthly cost to keep PageCast live as a solopreneur. | B2: Recurring monthly cost to keep PageCast live as a solopreneur. | C2: Recurring monthly cost to keep PageCast live as a solopreneur. | D2: Recurring monthly cost to keep PageCast live as a solopreneur. | E2: Recurring monthly cost to keep PageCast live as a solopreneur. | F2: Recurring monthly cost to keep PageCast live as a solopreneur. | G2: Recurring monthly cost to keep PageCast live as a solopreneur. | H2: Recurring monthly cost to keep PageCast live as a solopreneur.
A4: Item | B4: Lean | C4: Recommended | D4: Safer Launch | E4: Selected | F4: Category | G4: Notes
A5: =Assumptions!A24 -> Hosting - Vercel | B5: =Assumptions!B24 -> 0 | C5: =Assumptions!C24 -> 20 | D5: =Assumptions!D24 -> 20 | E5: =INDEX(B5:D5,1,MATCH(Assumptions!$B$5,$B$4:$D$4,0)) -> 20 | F5: =Assumptions!E24 -> Infrastructure | G5: =Assumptions!F24 -> Hobby for early tests; Pro for production/commercial use
A6: =Assumptions!A25 -> Database/Auth - Supabase | B6: =Assumptions!B25 -> 0 | C6: =Assumptions!C25 -> 25 | D6: =Assumptions!D25 -> 25 | E6: =INDEX(B6:D6,1,MATCH(Assumptions!$B$5,$B$4:$D$4,0)) -> 25 | F6: =Assumptions!E25 -> Infrastructure | G6: =Assumptions!F25 -> Free for early tests; Pro recommended before launch
A7: =Assumptions!A26 -> Object storage - Cloudflare R2 | B7: =Assumptions!B26 -> 3 | C7: =Assumptions!C26 -> 8 | D7: =Assumptions!D26 -> 20 | E7: =INDEX(B7:D7,1,MATCH(Assumptions!$B$5,$B$4:$D$4,0)) -> 8 | F7: =Assumptions!E26 -> Infrastructure | G7: =Assumptions!F26 -> Audio/covers storage buffer; usage based
A8: =Assumptions!A27 -> Transactional email - Resend | B8: =Assumptions!B27 -> 0 | C8: =Assumptions!C27 -> 20 | D8: =Assumptions!D27 -> 20 | E8: =INDEX(B8:D8,1,MATCH(Assumptions!$B$5,$B$4:$D$4,0)) -> 20 | F8: =Assumptions!E27 -> Email | G8: =Assumptions!F27 -> Free tier initially; Pro if volume/branding requires
A9: =Assumptions!A28 -> Business email - Google/Zoho | B9: =Assumptions!B28 -> 1 | C9: =Assumptions!C28 -> 7 | D9: =Assumptions!D28 -> 7 | E9: =INDEX(B9:D9,1,MATCH(Assumptions!$B$5,$B$4:$D$4,0)) -> 7 | F9: =Assumptions!E28 -> Email | G9: =Assumptions!F28 -> One solopreneur inbox
A10: =Assumptions!A29 -> AI text / assistant tools | B10: =Assumptions!B29 -> 20 | C10: =Assumptions!C29 -> 40 | D10: =Assumptions!D29 -> 80 | E10: =INDEX(B10:D10,1,MATCH(Assumptions!$B$5,$B$4:$D$4,0)) -> 40 | F10: =Assumptions!E29 -> AI tools | G10: =Assumptions!F29 -> Writing, support, content ops
A11: =Assumptions!A30 -> AI voice / TTS credits | B11: =Assumptions!B30 -> 6 | C11: =Assumptions!C30 -> 22 | D11: =Assumptions!D30 -> 99 | E11: =INDEX(B11:D11,1,MATCH(Assumptions!$B$5,$B$4:$D$4,0)) -> 22 | F11: =Assumptions!E30 -> Audio | G11: =Assumptions!F30 -> Starter/creator/pro depending on production needs
A12: =Assumptions!A31 -> Design tools | B12: =Assumptions!B31 -> 0 | C12: =Assumptions!C31 -> 15 | D12: =Assumptions!D31 -> 20 | E12: =INDEX(B12:D12,1,MATCH(Assumptions!$B$5,$B$4:$D$4,0)) -> 15 | F12: =Assumptions!E31 -> Creative | G12: =Assumptions!F31 -> Canva or equivalent
A13: =Assumptions!A32 -> Analytics / monitoring | B13: =Assumptions!B32 -> 0 | C13: =Assumptions!C32 -> 0 | D13: =Assumptions!D32 -> 20 | E13: =INDEX(B13:D13,1,MATCH(Assumptions!$B$5,$B$4:$D$4,0)) -> 0 | F13: =Assumptions!E32 -> Infrastructure | G13: =Assumptions!F32 -> Free tier first; paid monitoring buffer
A14: =Assumptions!A33 -> Accounting / invoicing tools | B14: =Assumptions!B33 -> 0 | C14: =Assumptions!C33 -> 15 | D14: =Assumptions!D33 -> 30 | E14: =INDEX(B14:D14,1,MATCH(Assumptions!$B$5,$B$4:$D$4,0)) -> 15 | F14: =Assumptions!E33 -> Operations | G14: =Assumptions!F33 -> May start with spreadsheets
A15: =Assumptions!A34 -> Legal/compliance reserve | B15: =Assumptions!B34 -> 50 | C15: =Assumptions!C34 -> 150 | D15: =Assumptions!D34 -> 300 | E15: =INDEX(B15:D15,1,MATCH(Assumptions!$B$5,$B$4:$D$4,0)) -> 150 | F15: =Assumptions!E34 -> Operations | G15: =Assumptions!F34 -> Monthly reserve for reviews, notices, admin
A16: =Assumptions!A35 -> Customer support / moderation reserve | B16: =Assumptions!B35 -> 0 | C16: =Assumptions!C35 -> 50 | D16: =Assumptions!D35 -> 150 | E16: =INDEX(B16:D16,1,MATCH(Assumptions!$B$5,$B$4:$D$4,0)) -> 50 | F16: =Assumptions!E35 -> Operations | G16: =Assumptions!F35 -> Solo time plus occasional help
... A19: =Assumptions!A38 -> Misc SaaS buffer | B19: =Assumptions!B38 -> 25 | C19: =Assumptions!C38 -> 75 | D19: =Assumptions!D38 -> 150 | E19: =INDEX(B19:D19,1,MATCH(Assumptions!$B$5,$B$4:$D$4,0)) -> 75 | F19: =Assumptions!E38 -> Operations | G19: =Assumptions!F38 -> Unexpected tools, plugins, templates
A20: Total monthly opex | B20: =SUM(B5:B19) -> 305 | C20: =SUM(C5:C19) -> 1097 | D20: =SUM(D5:D19) -> 2841 | E20: =SUM(E5:E19) -> 1097

Sheet 12-Month Cash Plan
A1: 12-Month Cash Plan | B1: 12-Month Cash Plan | C1: 12-Month Cash Plan | D1: 12-Month Cash Plan | E1: 12-Month Cash Plan | F1: 12-Month Cash Plan | G1: 12-Month Cash Plan | H1: 12-Month Cash Plan | I1: 12-Month Cash Plan | J1: 12-Month Cash Plan | K1: 12-Month Cash Plan | L1: 12-Month Cash Plan | M1: 12-Month Cash Plan | N1: 12-Month Cash Plan
A2: Simple cash runway model for the selected scenario. | B2: Simple cash runway model for the selected scenario. | C2: Simple cash runway model for the selected scenario. | D2: Simple cash runway model for the selected scenario. | E2: Simple cash runway model for the selected scenario. | F2: Simple cash runway model for the selected scenario. | G2: Simple cash runway model for the selected scenario. | H2: Simple cash runway model for the selected scenario.
A4: Metric | B4: M1 | C4: M2 | D4: M3 | E4: M4 | F4: M5 | G4: M6 | H4: M7 | I4: M8 | J4: M9 | K4: M10 | L4: M11 | M4: M12 | N4: Total
A5: Beginning cash | B5: =INDEX(Assumptions!$B$43:$D$43,1,MATCH(Assumptions!$B$5,Assumptions!$B$42:$D$42,0)) -> 8000 | C5: =B12 -> 2217.9 | D5: =C12 -> 1120.9 | E5: =D12 -> 23.9 | F5: =E12 -> -1036.6913 | G5: =F12 -> -2060.8738 | H5: =G12 -> -3048.6475 | I5: =H12 -> -4000.0125 | J5: =I12 -> -4914.9688 | ... M5: =L12 -> -7441.385 | N5: =M5 -> -7441.385
A6: One-time setup spend | B6: ='Setup Budget'!E16 -> 4685.1 | C6: =0 -> 0 | D6: =0 -> 0 | E6: =0 -> 0 | F6: =0 -> 0 | G6: =0 -> 0 | H6: =0 -> 0 | I6: =0 -> 0 | J6: =0 -> 0 | ... M6: =0 -> 0 | N6: =SUM(B6:M6) -> 4685.1
A7: Monthly opex | B7: ='Monthly Opex'!E20 -> 1097 | C7: ='Monthly Opex'!E20 -> 1097 | D7: ='Monthly Opex'!E20 -> 1097 | E7: ='Monthly Opex'!E20 -> 1097 | F7: ='Monthly Opex'!E20 -> 1097 | G7: ='Monthly Opex'!E20 -> 1097 | H7: ='Monthly Opex'!E20 -> 1097 | I7: ='Monthly Opex'!E20 -> 1097 | J7: ='Monthly Opex'!E20 -> 1097 | K7: ='Monthly Opex'!E20 -> 1097 | L7: ='Monthly Opex'!E20 -> 1097 | M7: ='Monthly Opex'!E20 -> 1097 | N7: =SUM(B7:M7) -> 13164
A8: Gross revenue | B8: =IF(1<=INDEX(Assumptions!$B$44:$D$44,1,MATCH(Assumptions!$B$5,Assumptions!$B$42:$D$42,0)),0,MAX(0,(1-INDEX(Assumptions!$B$44:$D$44,1,MATCH(Assumptions!$B$5,Assumptions!$B$42:$D$42,0)))*25)*INDEX(Assumptions!$B$45:$D$45,1,MATCH(Assumptions!$B$5,Assumptions!$B$42:$D$42,0))) -> 0 | C8: =IF(2<=INDEX(Assumptions!$B$44:$D$44,1,MATCH(Assumptions!$B$5,Assumptions!$B$42:$D$42,0)),0,MAX(0,(2-INDEX(Assumptions!$B$44:$D$44,1,MATCH(Assumptions!$B$5,Assumptions!$B$42:$D$42,0)))*25)*INDEX(Assumptions!$B$45:$D$45,1,MATCH(Assumptions!$B$5,Assumptions!$B$42:$D$42,0))) -> 0 | D8: =IF(3<=INDEX(Assumptions!$B$44:$D$44,1,MATCH(Assumptions!$B$5,Assumptions!$B$42:$D$42,0)),0,MAX(0,(3-INDEX(Assumptions!$B$44:$D$44,1,MATCH(Assumptions!$B$5,Assumptions!$B$42:$D$42,0)))*25)*INDEX(Assumptions!$B$45:$D$45,1,MATCH(Assumptions!$B$5,Assumptions!$B$42:$D$42,0))) -> 0 | E8: =IF(4<=INDEX(Assumptions!$B$44:$D$44,1,MATCH(Assumptions!$B$5,Assumptions!$B$42:$D$42,0)),0,MAX(0,(4-INDEX(Assumptions!$B$44:$D$44,1,MATCH(Assumptions!$B$5,Assumptions!$B$42:$D$42,0)))*25)*INDEX(Assumptions!$B$45:$D$45,1,MATCH(Assumptions!$B$5,Assumptions!$B$42:$D$42,0))) -> 99.75 | F8: =IF(5<=INDEX(Assumptions!$B$44:$D$44,1,MATCH(Assumptions!$B$5,Assumptions!$B$42:$D$42,0)),0,MAX(0,(5-INDEX(Assumptions!$B$44:$D$44,1,MATCH(Assumptions!$B$5,Assumptions!$B$42:$D$42,0)))*25)*INDEX(Assumptions!$B$45:$D$45,1,MATCH(Assumptions!$B$5,Assumptions!$B$42:$D$42,0))) -> 199.5 | G8: =IF(6<=INDEX(Assumptions!$B$44:$D$44,1,MATCH(Assumptions!$B$5,Assumptions!$B$42:$D$42,0)),0,MAX(0,(6-INDEX(Assumptions!$B$44:$D$44,1,MATCH(Assumptions!$B$5,Assumptions!$B$42:$D$42,0)))*25)*INDEX(Assumptions!$B$45:$D$45,1,MATCH(Assumptions!$B$5,Assumptions!$B$42:$D$42,0))) -> 299.25 | H8: =IF(7<=INDEX(Assumptions!$B$44:$D$44,1,MATCH(Assumptions!$B$5,Assumptions!$B$42:$D$42,0)),0,MAX(0,(7-INDEX(Assumptions!$B$44:$D$44,1,MATCH(Assumptions!$B$5,Assumptions!$B$42:$D$42,0)))*25)*INDEX(Assumptions!$B$45:$D$45,1,MATCH(Assumptions!$B$5,Assumptions!$B$42:$D$42,0))) -> 399 | I8: =IF(8<=INDEX(Assumptions!$B$44:$D$44,1,MATCH(Assumptions!$B$5,Assumptions!$B$42:$D$42,0)),0,MAX(0,(8-INDEX(Assumptions!$B$44:$D$44,1,MATCH(Assumptions!$B$5,Assumptions!$B$42:$D$42,0)))*25)*INDEX(Assumptions!$B$45:$D$45,1,MATCH(Assumptions!$B$5,Assumptions!$B$42:$D$42,0))) -> 498.75 | J8: =IF(9<=INDEX(Assumptions!$B$44:$D$44,1,MATCH(Assumptions!$B$5,Assumptions!$B$42:$D$42,0)),0,MAX(0,(9-INDEX(Assumptions!$B$44:$D$44,1,MATCH(Assumptions!$B$5,Assumptions!$B$42:$D$42,0)))*25)*INDEX(Assumptions!$B$45:$D$45,1,MATCH(Assumptions!$B$5,Assumptions!$B$42:$D$42,0))) -> 598.5 | K8: =IF(10<=INDEX(Assumptions!$B$44:$D$44,1,MATCH(Assumptions!$B$5,Assumptions!$B$42:$D$42,0)),0,MAX(0,(10-INDEX(Assumptions!$B$44:$D$44,1,MATCH(Assumptions!$B$5,Assumptions!$B$42:$D$42,0)))*25)*INDEX(Assumptions!$B$45:$D$45,1,MATCH(Assumptions!$B$5,Assumptions!$B$42:$D$42,0))) -> 698.25 | L8: =IF(11<=INDEX(Assumptions!$B$44:$D$44,1,MATCH(Assumptions!$B$5,Assumptions!$B$42:$D$42,0)),0,MAX(0,(11-INDEX(Assumptions!$B$44:$D$44,1,MATCH(Assumptions!$B$5,Assumptions!$B$42:$D$42,0)))*25)*INDEX(Assumptions!$B$45:$D$45,1,MATCH(Assumptions!$B$5,Assumptions!$B$42:$D$42,0))) -> 798 | M8: =IF(12<=INDEX(Assumptions!$B$44:$D$44,1,MATCH(Assumptions!$B$5,Assumptions!$B$42:$D$42,0)),0,MAX(0,(12-INDEX(Assumptions!$B$44:$D$44,1,MATCH(Assumptions!$B$5,Assumptions!$B$42:$D$42,0)))*25)*INDEX(Assumptions!$B$45:$D$45,1,MATCH(Assumptions!$B$5,Assumptions!$B$42:$D$42,0))) -> 897.75 | N8: =SUM(B8:M8) -> 4488.75
A9: Creator payouts | B9: =B8*INDEX(Assumptions!$B$46:$D$46,1,MATCH(Assumptions!$B$5,Assumptions!$B$42:$D$42,0)) -> 0 | C9: =C8*INDEX(Assumptions!$B$46:$D$46,1,MATCH(Assumptions!$B$5,Assumptions!$B$42:$D$42,0)) -> 0 | D9: =D8*INDEX(Assumptions!$B$46:$D$46,1,MATCH(Assumptions!$B$5,Assumptions!$B$42:$D$42,0)) -> 0 | E9: =E8*INDEX(Assumptions!$B$46:$D$46,1,MATCH(Assumptions!$B$5,Assumptions!$B$42:$D$42,0)) -> 59.85 | F9: =F8*INDEX(Assumptions!$B$46:$D$46,1,MATCH(Assumptions!$B$5,Assumptions!$B$42:$D$42,0)) -> 119.7 | G9: =G8*INDEX(Assumptions!$B$46:$D$46,1,MATCH(Assumptions!$B$5,Assumptions!$B$42:$D$42,0)) -> 179.55 | H9: =H8*INDEX(Assumptions!$B$46:$D$46,1,MATCH(Assumptions!$B$5,Assumptions!$B$42:$D$42,0)) -> 239.4 | I9: =I8*INDEX(Assumptions!$B$46:$D$46,1,MATCH(Assumptions!$B$5,Assumptions!$B$42:$D$42,0)) -> 299.25 | ... M9: =M8*INDEX(Assumptions!$B$46:$D$46,1,MATCH(Assumptions!$B$5,Assumptions!$B$42:$D$42,0)) -> 538.65 | N9: =SUM(B9:M9) -> 2693.25
A10: Payment fees | B10: =B8*INDEX(Assumptions!$B$47:$D$47,1,MATCH(Assumptions!$B$5,Assumptions!$B$42:$D$42,0)) -> 0 | C10: =C8*INDEX(Assumptions!$B$47:$D$47,1,MATCH(Assumptions!$B$5,Assumptions!$B$42:$D$42,0)) -> 0 | D10: =D8*INDEX(Assumptions!$B$47:$D$47,1,MATCH(Assumptions!$B$5,Assumptions!$B$42:$D$42,0)) -> 0 | E10: =E8*INDEX(Assumptions!$B$47:$D$47,1,MATCH(Assumptions!$B$5,Assumptions!$B$42:$D$42,0)) -> 3.49125 | F10: =F8*INDEX(Assumptions!$B$47:$D$47,1,MATCH(Assumptions!$B$5,Assumptions!$B$42:$D$42,0)) -> 6.9825 | G10: =G8*INDEX(Assumptions!$B$47:$D$47,1,MATCH(Assumptions!$B$5,Assumptions!$B$42:$D$42,0)) -> 10.47375 | H10: =H8*INDEX(Assumptions!$B$47:$D$47,1,MATCH(Assumptions!$B$5,Assumptions!$B$42:$D$42,0)) -> 13.965 | I10: =I8*INDEX(Assumptions!$B$47:$D$47,1,MATCH(Assumptions!$B$5,Assumptions!$B$42:$D$42,0)) -> 17.45625 | ... M10: =M8*INDEX(Assumptions!$B$47:$D$47,1,MATCH(Assumptions!$B$5,Assumptions!$B$42:$D$42,0)) -> 31.42125 | N10: =SUM(B10:M10) -> 157.10625
A11: Net cash flow | B11: =B8-B9-B10-B6-B7 -> -5782.1 | C11: =C8-C9-C10-C6-C7 -> -1097 | D11: =D8-D9-D10-D6-D7 -> -1097 | E11: =E8-E9-E10-E6-E7 -> -1060.5912 | F11: =F8-F9-F10-F6-F7 -> -1024.1825 | G11: =G8-G9-G10-G6-G7 -> -987.77375 | H11: =H8-H9-H10-H6-H7 -> -951.365 | I11: =I8-I9-I10-I6-I7 -> -914.95625 | ... M11: =M8-M9-M10-M6-M7 -> -769.32125 | N11: =SUM(B11:M11) -> -16210.706
A12: Ending cash | B12: =B5+B11 -> 2217.9 | C12: =C5+C11 -> 1120.9 | D12: =D5+D11 -> 23.9 | E12: =E5+E11 -> -1036.6913 | F12: =F5+F11 -> -2060.8738 | G12: =G5+G11 -> -3048.6475 | H12: =H5+H11 -> -4000.0125 | I12: =I5+I11 -> -4914.9688 | ... M12: =M5+M11 -> -8210.7062 | N12: =M12 -> -8210.7062
A13: Minimum extra funding needed | B13: =MAX(0,-B12) -> 0 | C13: =MAX(0,-C12) -> 0 | D13: =MAX(0,-D12) -> 0 | E13: =MAX(0,-E12) -> 1036.6913 | F13: =MAX(0,-F12) -> 2060.8738 | G13: =MAX(0,-G12) -> 3048.6475 | H13: =MAX(0,-H12) -> 4000.0125 | I13: =MAX(0,-I12) -> 4914.9688 | ... M13: =MAX(0,-M12) -> 8210.7062 | N13: =SUM(B13:M13) -> 43142.456
A14: Runway status | B14: =IF(B12>=0,"OK","Needs funding") -> OK | C14: =IF(C12>=0,"OK","Needs funding") -> OK | D14: =IF(D12>=0,"OK","Needs funding") -> OK | E14: =IF(E12>=0,"OK","Needs funding") -> Needs funding | F14: =IF(F12>=0,"OK","Needs funding") -> Needs funding | G14: =IF(G12>=0,"OK","Needs funding") -> Needs funding | H14: =IF(H12>=0,"OK","Needs funding") -> Needs funding | I14: =IF(I12>=0,"OK","Needs funding") -> Needs funding | ... M14: =IF(M12>=0,"OK","Needs funding") -> Needs funding | N14: =IF(COUNTIF(B14:M14,"Needs funding")=0,"OK","Needs funding") -> Needs funding

Sheet Service Stack
A1: Recommended Service Stack | B1: Recommended Service Stack | C1: Recommended Service Stack | D1: Recommended Service Stack | E1: Recommended Service Stack | F1: Recommended Service Stack
A2: Practical default setup for a PageCast solopreneur launch.
A4: Area | B4: Recommended Tool | C4: Monthly Budget | D4: Annual/Setup | E4: Priority | F4: Why
A5: Domain/DNS | B5: Cloudflare Registrar + DNS | C5: 0 | D5: 15 | E5: Must-have | F5: Low-renewal domain, strong DNS, SSL/CDN basics
A6: Hosting | B6: Vercel Pro | C6: 20 | D6: 0 | E6: Must-have | F6: Production Next.js hosting for reader/studio apps
A7: Database/Auth | B7: Supabase Pro | C7: 25 | D7: 0 | E7: Must-have | F7: Postgres, Auth, Storage/RLS; Pro before serious public launch
A8: Object Storage | B8: Cloudflare R2 | C8: 8 | D8: 0 | E8: Must-have | F8: Audio and cover storage with no egress fees
A9: Transactional Email | B9: Resend | C9: 20 | D9: 0 | E9: Should-have | F9: Login, purchase, creator/admin notifications
A10: Business Email | B10: Google Workspace | C10: 7 | D10: 84 | E10: Must-have | F10: Domain email and trust for support/legal contact
A11: Payments | B11: Stripe | C11: 0 | D11: 0 | E11: Must-have | F11: No fixed monthly fee; variable processing fees
A12: AI Text | B12: OpenAI API / ChatGPT | C12: 40 | D12: 0 | E12: Should-have | F12: Story editing, content ops, support, metadata
A13: AI Voice | B13: ElevenLabs or OpenAI TTS | C13: 22 | D13: 0 | E13: Should-have | F13: Narration/character voice production
A14: Design | B14: Canva or equivalent | C14: 15 | D14: 0 | E14: Could defer | F14: Launch graphics and social/video assets
A15: Analytics | B15: Free tier first | C15: 0 | D15: 0 | E15: Should-have | F15: Track funnel, activation, story completion
A16: Accounting | B16: Spreadsheet first | C16: 0 | D16: 0 | E16: Could defer | F16: Upgrade when revenue starts
... A18: Marketing | B18: Paid test budget | C18: 500 | D18: 0 | E18: Must-have | F18: Validate parent and creator demand

Sheet Launch Marketing
A1: Launch Marketing Budget | B1: Launch Marketing Budget | C1: Launch Marketing Budget | D1: Launch Marketing Budget | E1: Launch Marketing Budget | F1: Launch Marketing Budget
A2: First 90-day launch spend plan focused on proof, not vanity.
A4: Channel / Activity | B4: Month 1 | C4: Month 2 | D4: Month 3 | E4: Total | F4: Goal
A5: Short-form demo production | B5: 150 | C5: 150 | D5: 150 | E5: =SUM(B5:D5) -> 450 | F5: Create 10-20 clips comparing ebook/audiobook/PageCast
A6: TikTok/Reels paid tests | B6: 150 | C6: 250 | D6: 350 | E6: =SUM(B6:D6) -> 750 | F6: Find parent/creator messages that convert
A7: Parent/community collaborations | B7: 100 | C7: 150 | D7: 200 | E7: =SUM(B7:D7) -> 450 | F7: Islamic parenting, homeschool, teacher groups
A8: Creator pilot incentives | B8: 100 | C8: 150 | D8: 250 | E8: =SUM(B8:D8) -> 500 | F8: Get early authors/educators to publish
A9: Beta family rewards/giveaways | B9: 50 | C9: 75 | D9: 100 | E9: =SUM(B9:D9) -> 225 | F9: Encourage testimonials and referrals
A10: Email/landing copy/tools | B10: 25 | C10: 25 | D10: 25 | E10: =SUM(B10:D10) -> 75 | F10: Lead capture and onboarding polish
A11: PR/community outreach | B11: 0 | C11: 50 | D11: 100 | E11: =SUM(B11:D11) -> 150 | F11: Local press, education communities
A12: Buffer | B12: 25 | C12: 50 | D12: 75 | E12: =SUM(B12:D12) -> 150 | F12: Unplanned creative tests
A13: Total | B13: =SUM(B5:B12) -> 600 | C13: =SUM(C5:C12) -> 900 | D13: =SUM(D5:D12) -> 1250 | E13: =SUM(E5:E12) -> 2750

Sheet Sources
A1: Pricing Sources | B1: Pricing Sources | C1: Pricing Sources | D1: Pricing Sources
A2: Current public pricing references checked on 2026-05-17. Confirm exact checkout pricing before purchase.
A4: Cost Area | B4: Source | C4: URL | D4: Notes
A5: Hosting | B5: Vercel Pricing | C5: https://vercel.com/pricing | D5: Pro listed at $20/month
A6: Hosting plan docs | B6: Vercel Account Plans | C6: https://vercel.com/docs/plans | D6: Hobby, Pro, Enterprise plan context
A7: Database/Auth | B7: Supabase Pricing | C7: https://supabase.com/pricing | D7: Pro commonly listed at $25/month; free tier available
A8: Object storage | B8: Cloudflare R2 Pricing | C8: https://developers.cloudflare.com/r2/pricing/ | D8: Storage and Class A/B operations; no egress fees
A9: Domain registrar | B9: Cloudflare Registrar | C9: https://developers.cloudflare.com/registrar/ | D9: At-cost domain registration/renewal model
A10: Domain alternative | B10: Namecheap Domains | C10: https://www.namecheap.com/domains/ | D10: Domain search and registrar pricing reference
A11: Business email | B11: Google Workspace Pricing | C11: https://workspace.google.com/intl/en/pricing/ | D11: Business Starter pricing and email/storage feature reference
A12: Low-cost email | B12: Zoho Workplace PDF | C12: https://www.zoho.com.cn/sites/default/files/workplace/zoho-workplace-plan-comparison-usd.pdf | D12: Mail Lite around $1/user/month annually
A13: Transactional email | B13: Resend Pricing | C13: https://resend.com/pricing | D13: Free/pro transactional email plans
A14: Payments | B14: Stripe Malaysia Pricing | C14: https://stripe.com/en-my/pricing | D14: Variable transaction fees; no fixed monthly fee assumed
A15: AI/API | B15: OpenAI API Pricing | C15: https://openai.com/api/pricing/ | D15: AI text/audio cost reference
... A18: Internal model | B18: PageCast Business Model | C18: outputs/pagecast_business_model/PageCast_Business_Model.xlsx | D18: Business model workbook created earlier

Sheet Checks
A1: Model Checks | B1: Model Checks | C1: Model Checks | D1: Model Checks | E1: Model Checks | F1: Model Checks
A2: Budget tie-outs for launch budget workbook.
A4: Check | B4: Actual | C4: Expected | D4: Difference | E4: Status | F4: Notes
A5: Setup selected total ties | B5: ='Setup Budget'!E16 -> 4685.1 | C5: ='Setup Budget'!E14+'Setup Budget'!E15 -> 4685.1 | D5: =B5-C5 -> 0 | E5: =IF(ABS(D5)<1,"OK","Check") -> OK | F5: Setup Budget selected equals subtotal plus contingency
A6: Monthly selected total ties | B6: ='Monthly Opex'!E20 -> 1097 | C6: =SUM('Monthly Opex'!E5:E19) -> 1097 | D6: =B6-C6 -> 0 | E6: =IF(ABS(D6)<1,"OK","Check") -> OK | F6: Monthly Opex selected equals sum of selected items
A7: Cash plan total funding ties | B7: ='12-Month Cash Plan'!N13 -> 43142.456 | C7: =SUM('12-Month Cash Plan'!B13:M13) -> 43142.456 | D7: =B7-C7 -> 0 | E7: =IF(ABS(D7)<1,"OK","Check") -> OK | F7: Total funding equals sum of monthly funding needs
A8: Ending cash formula final month | B8: ='12-Month Cash Plan'!M12 -> -8210.7062 | C8: ='12-Month Cash Plan'!M5+'12-Month Cash Plan'!M11 -> -8210.7062 | D8: =B8-C8 -> 0 | E8: =IF(ABS(D8)<1,"OK","Check") -> OK | F8: Ending cash equals beginning cash plus net cash flow in M12
A9: Model status | E9: =IF(COUNTIF(E5:E8,"Check")=0,"OK","Review") -> OK | F9: All checks should show OK
